SteamedBun/__init__.py
SteamedBun/_BrowseTools/BrowserFormat.py
SteamedBun/_BrowseTools/__init__.py
SteamedBun/_BrowseTools/browser_session.yaml
SteamedBun/_ConfigTools/Config.py
SteamedBun/_ConfigTools/__init__.py
SteamedBun/_ConfigTools/config.ini
SteamedBun/_DBTools/DBFormat.py
SteamedBun/_DBTools/__init__.py
SteamedBun/_DecoratorTools/CaseDecorator.py
SteamedBun/_DecoratorTools/DecoratorFormat.py
SteamedBun/_DecoratorTools/__init__.py
SteamedBun/_EmailTools/EmailFormat.py
SteamedBun/_EmailTools/__init__.py
SteamedBun/_ExceptionTools/ExceptionCatch.py
SteamedBun/_ExceptionTools/__init__.py
SteamedBun/_ExpectTools/ExpectFormat.py
SteamedBun/_ExpectTools/__init__.py
SteamedBun/_FileTools/FileOperateFormat.py
SteamedBun/_FileTools/InitPytestProject.py
SteamedBun/_FileTools/__init__.py
SteamedBun/_InterfaceCoverageTools/InterfaceCoverageFormat.py
SteamedBun/_InterfaceCoverageTools/__init__.py
SteamedBun/_LoggerTools/Logger.py
SteamedBun/_LoggerTools/__init__.py
SteamedBun/_NumberTools/NumberFormat.py
SteamedBun/_NumberTools/__init__.py
SteamedBun/_Poium/__init__.py
SteamedBun/_Poium/config.py
SteamedBun/_Poium/javascript.py
SteamedBun/_Poium/playwright.py
SteamedBun/_Poium/selenium.py
SteamedBun/_Poium/webdriver.py
SteamedBun/_Poium/processing/__init__.py
SteamedBun/_Poium/processing/font/song.ttc
SteamedBun/_Poium/universal/__init__.py
SteamedBun/_Poium/universal/exceptions.py
SteamedBun/_Poium/universal/func_timeout.py
SteamedBun/_Poium/universal/selector.py
SteamedBun/_RequestTools/HttpRequest.py
SteamedBun/_RequestTools/__init__.py
SteamedBun/_SingletonTools/Singleton.py
SteamedBun/_SingletonTools/__init__.py
SteamedBun/_TimeTools/TimeFormat.py
SteamedBun/_TimeTools/__init__.py
SteamedBun/_TipProject/__init__.py
steamedbun-2.3.0.dist-info/licenses/LICENSE
steamedbun-2.3.0.dist-info/METADATA
steamedbun-2.3.0.dist-info/WHEEL
steamedbun-2.3.0.dist-info/entry_points.txt
steamedbun-2.3.0.dist-info/top_level.txt
steamedbun-2.3.0.dist-info/RECORD
