Metadata-Version: 2.4
Name: steamedbun
Version: 2.3.0
Summary: 馒头的第三方库
Home-page: https://github.com/neihanshenshou/SteamedBun
Author: 馒头
Author-email: neihanshenshou@163.com
License: Apache License 2.0
Platform: MacOS、Window
Requires-Python: >=3.5
License-File: LICENSE
Requires-Dist: allure-pytest==2.15.3
Requires-Dist: colorama==0.4.6
Requires-Dist: NumPy==1.23.5
Requires-Dist: openpyxl==3.1.0
Requires-Dist: pandas>=2.0.3
Requires-Dist: Pillow==9.5.0
Requires-Dist: playwright==1.44.0
Requires-Dist: pymysql==1.1.1
Requires-Dist: python-dateutil==2.8.2
Requires-Dist: pytest>=7.3.2
Requires-Dist: pytest-ordering==0.6
Requires-Dist: pytest-repeat==0.9.4
Requires-Dist: pytest-xdist==3.5.0
Requires-Dist: pytest-cov==7.0.0
Requires-Dist: PyYAML==6.0.3
Requires-Dist: requests==2.30.0
Requires-Dist: retry==0.9.2
Requires-Dist: selenium==4.4.3
Requires-Dist: setuptools>=60.2.0
Requires-Dist: SteamedBun-Uninstall==1.0.0
Requires-Dist: urllib3==1.26.12
Dynamic: author
Dynamic: author-email
Dynamic: description
Dynamic: description-content-type
Dynamic: home-page
Dynamic: license
Dynamic: license-file
Dynamic: platform
Dynamic: requires-dist
Dynamic: requires-python
Dynamic: summary
